README.md
setup.py
Conquer.egg-info/PKG-INFO
Conquer.egg-info/SOURCES.txt
Conquer.egg-info/dependency_links.txt
Conquer.egg-info/top_level.txt
conquer/__init__.py
conquer/main.py
conquer/script.py