Metadata-Version: 1.0
Name: Conquer
Version: 0.0.2
Summary: Conquer runs commands
Home-page: https://github.com/bertrandchenal/conquer
Author: Bertrand Chenal
Author-email: bertrand@adimian.com
License: MIT
Platform: UNKNOWN
